SCTrack/__init__.py
SCTrack/base.py
SCTrack/config.py
SCTrack/feature.py
SCTrack/generate_tracking_stack.py
SCTrack/prepare.py
SCTrack/reclassification.py
SCTrack/sctrack.py
SCTrack/t_error.py
SCTrack/template.py
SCTrack/track.py
SCTrack/tracker.py
SCTrack/utils.py
SC_Track-0.0.9.dist-info/LICENSE
SC_Track-0.0.9.dist-info/METADATA
SC_Track-0.0.9.dist-info/WHEEL
SC_Track-0.0.9.dist-info/entry_points.txt
SC_Track-0.0.9.dist-info/top_level.txt
SC_Track-0.0.9.dist-info/RECORD
