Metadata-Version: 2.1
Name: SC-Track
Version: 0.0.9
Summary: single cell tracking package
Home-page: https://github.com/frozenleaves/SC-Track
Author: Li Chengxin
Author-email: 914814442@qq.com
License: GNU General Public License v3.0
Requires-Python: >=3.7
License-File: LICENSE
Requires-Dist: numpy (>=1.21.6)
Requires-Dist: shapely (>=2.0.1)
Requires-Dist: numba (>=0.55.2)
Requires-Dist: matplotlib (>=3.5.1)
Requires-Dist: imagesize (>=1.3.0)
Requires-Dist: scikit-image (>=0.19.2)
Requires-Dist: tifffile (>=2021.11.2)
Requires-Dist: opencv-python (>=4.5.5.64)
Requires-Dist: scipy (>=1.7.3)
Requires-Dist: scikit-learn (>=1.0.2)
Requires-Dist: tqdm (>=4.64.0)
Requires-Dist: treelib (>=1.6.4)
Requires-Dist: pandas (>=1.3.5)
Requires-Dist: openpyxl (>=3.0.10)
Requires-Dist: pylibtiff (>=0.4.2)
